LICENSE
MANIFEST.in
README.md
setup.cfg
setup.py
strawberry_django_graphiql_voyager/__init__.py
strawberry_django_graphiql_voyager/views.py
strawberry_django_graphiql_voyager.egg-info/PKG-INFO
strawberry_django_graphiql_voyager.egg-info/SOURCES.txt
strawberry_django_graphiql_voyager.egg-info/dependency_links.txt
strawberry_django_graphiql_voyager.egg-info/top_level.txt
strawberry_django_graphiql_voyager/static/strawberry_django_graphiql_voyager/graphiql/css/11.66866c8b.chunk.css
strawberry_django_graphiql_voyager/static/strawberry_django_graphiql_voyager/graphiql/css/11.66866c8b.chunk.css.map
strawberry_django_graphiql_voyager/static/strawberry_django_graphiql_voyager/graphiql/css/main.d0b1e8f9.chunk.css
strawberry_django_graphiql_voyager/static/strawberry_django_graphiql_voyager/graphiql/css/main.d0b1e8f9.chunk.css.map
strawberry_django_graphiql_voyager/static/strawberry_django_graphiql_voyager/graphiql/js/0.d69ee02e.chunk.js
strawberry_django_graphiql_voyager/static/strawberry_django_graphiql_voyager/graphiql/js/0.d69ee02e.chunk.js.map
strawberry_django_graphiql_voyager/static/strawberry_django_graphiql_voyager/graphiql/js/1.d76c06cc.chunk.js
strawberry_django_graphiql_voyager/static/strawberry_django_graphiql_voyager/graphiql/js/1.d76c06cc.chunk.js.map
strawberry_django_graphiql_voyager/static/strawberry_django_graphiql_voyager/graphiql/js/11.8fdec039.chunk.js
strawberry_django_graphiql_voyager/static/strawberry_django_graphiql_voyager/graphiql/js/11.8fdec039.chunk.js.map
strawberry_django_graphiql_voyager/static/strawberry_django_graphiql_voyager/graphiql/js/12.a9526db5.chunk.js
strawberry_django_graphiql_voyager/static/strawberry_django_graphiql_voyager/graphiql/js/12.a9526db5.chunk.js.map
strawberry_django_graphiql_voyager/static/strawberry_django_graphiql_voyager/graphiql/js/13.2ac64509.chunk.js
strawberry_django_graphiql_voyager/static/strawberry_django_graphiql_voyager/graphiql/js/13.2ac64509.chunk.js.map
strawberry_django_graphiql_voyager/static/strawberry_django_graphiql_voyager/graphiql/js/14.d5d84371.chunk.js
strawberry_django_graphiql_voyager/static/strawberry_django_graphiql_voyager/graphiql/js/14.d5d84371.chunk.js.map
