Metadata-Version: 2.1
Name: strawberry-django-graphiql-voyager
Version: 0.1.2
Summary: A Strawberry Django app that adds GraphiQL and Voyager to the graphql view
Home-page: https://github.com/mikedizon/strawberry-django-graphiql-voyager
Author: mikedizon
Author-email: mdizon@gmail.com
License: MIT
Classifier: Environment :: Web Environment
Classifier: Framework :: Django
Classifier: Intended Audience :: Developers
Classifier: License :: OSI Approved :: MIT License
Classifier: Operating System :: OS Independent
Classifier: Programming Language :: Python
Classifier: Programming Language :: Python :: 3 :: Only
Classifier: Programming Language :: Python :: 3.6
Classifier: Programming Language :: Python :: 3.7
Classifier: Programming Language :: Python :: 3.8
Classifier: Topic :: Internet :: WWW/HTTP
Classifier: Topic :: Internet :: WWW/HTTP :: Dynamic Content
License-File: LICENSE
